{
  "_fv": 24,
  "_type": "recipe",
  "definition": {
    "recipeType": "Crafting",
    "xpReward": 0.0,
    "cookingTime": 200,
    "recipeRetstackSize": 1,
    "group": "",
    "recipeShapeless": false,
    "recipeSlots": [
      {
        "value": "Blocks.CONCRETE#14"
      },
      {
        "value": ""
      },
      {
        "value": "Blocks.CONCRETE#14"
      },
      {
        "value": "Items.DYE#1"
      },
      {
        "value": "Blocks.IRON_BLOCK"
      },
      {
        "value": "Items.DYE#1"
      },
      {
        "value": ""
      },
      {
        "value": "Blocks.CONCRETE#14"
      },
      {
        "value": ""
      }
    ],
    "recipeReturnStack": {
      "value": "CUSTOM:SenjuArmor.body"
    },
    "name": "sa",
    "namespace": "mod"
  }
}